ta_cmi/__init__.py
ta_cmi/api.py
ta_cmi/channel.py
ta_cmi/cmi.py
ta_cmi/cmi_api.py
ta_cmi/cmi_channel.py
ta_cmi/coe.py
ta_cmi/coe_api.py
ta_cmi/coe_channel.py
ta_cmi/const.py
ta_cmi/device.py
ta_cmi-3.4.0.dist-info/licenses/LICENSE
ta_cmi-3.4.0.dist-info/METADATA
ta_cmi-3.4.0.dist-info/WHEEL
ta_cmi-3.4.0.dist-info/top_level.txt
ta_cmi-3.4.0.dist-info/RECORD
