Metadata-Version: 2.4
Name: ta-cmi
Version: 3.4.0
Summary: A Python wrapper to read out sensors from Technische Alternative using the C.M.I.
Author-email: DeerMaximum <git983456@parabelmail.de>
Maintainer-email: DeerMaximum <git983456@parabelmail.de>
License-Expression: MIT
Project-URL: homepage, https://gitlab.com/DeerMaximum/ta-cmi
Project-URL: repository, https://gitlab.com/DeerMaximum/ta-cmi
Keywords: api,wrapper,cmi,technische,alternative
Classifier: Development Status :: 5 - Production/Stable
Classifier: Framework :: AsyncIO
Classifier: Intended Audience :: Developers
Classifier: Intended Audience :: Information Technology
Classifier: Operating System :: OS Independent
Classifier: Programming Language :: Python
Classifier: Programming Language :: Python :: 3.13
Classifier: Topic :: Home Automation
Classifier: Topic :: Internet :: WWW/HTTP
Classifier: Topic :: Software Development
Requires-Python: >=3.13.2
License-File: LICENSE
Requires-Dist: aiohttp~=3.13.2
Requires-Dist: yarl~=1.22.0
Dynamic: license-file
